excel2xx/__init__.py
excel2xx/__main__.py
excel2xx/config.py
excel2xx/export.py
excel2xx/fieldmeta.py
excel2xx/fields.py
excel2xx/main.py
excel2xx/utils.py
excel2xx/version.py
excel2xx/codegen/__init__.py
excel2xx/console/__init__.py
excel2xx/console/colors.py
excel2xx/exporter/__init__.py
excel2xx/exporter/auto.py
excel2xx/validator/__init__.py
excel2xx-0.11.8.dist-info/LICENSE
excel2xx-0.11.8.dist-info/METADATA
excel2xx-0.11.8.dist-info/WHEEL
excel2xx-0.11.8.dist-info/entry_points.txt
excel2xx-0.11.8.dist-info/top_level.txt
excel2xx-0.11.8.dist-info/RECORD
