Metadata-Version: 2.1
Name: excel2xx
Version: 0.11.8
Summary: Extract data from excel file, and export to json, msgpack, or any code(mako template).
Home-page: https://github.com/cupen/excel2xx
Author: cupen
Author-email: xcupen@gmail.com
License: WTFPL
Classifier: Development Status :: 5 - Production/Stable
Classifier: Environment :: Console
Classifier: Intended Audience :: Developers
Classifier: Operating System :: OS Independent
Classifier: Programming Language :: Python
Classifier: Programming Language :: Python :: 3.8
Classifier: Programming Language :: Python :: 3.9
Classifier: Programming Language :: Python :: 3.10
Classifier: Programming Language :: Python :: 3.11
Classifier: Programming Language :: Python :: 3.12
Classifier: Programming Language :: Python :: Implementation :: CPython
Classifier: Topic :: Software Development :: Libraries :: Python Modules
Classifier: Topic :: Software Development :: Compilers
Classifier: Topic :: Software Development :: Code Generators
Requires-Python: >=3.8
License-File: LICENSE
Requires-Dist: xlrd ==1.2.*
Requires-Dist: openpyxl ==3.1.*
Requires-Dist: docopt >=0.6.0
Requires-Dist: mako >=1.3.0
Requires-Dist: msgpack-python >=0.4.8
Requires-Dist: colorama >=0.4.6
Requires-Dist: toml >=0.10.0
